tips_perflib/__init__.py
tips_perflib/data.py
tips_perflib/perfdisclib.py
tips_perflib-0.1.2.dist-info/WHEEL
tips_perflib-0.1.2.dist-info/METADATA
tips_perflib-0.1.2.dist-info/RECORD
