Metadata-Version: 2.1
Name: tips-perflib
Version: 0.1.2
Summary: 
Author: Vlad Rachev
Author-email: vlad.rachev@mongodb.com
Requires-Python: >=3.8,<3.11
Classifier: Programming Language :: Python :: 3
Classifier: Programming Language :: Python :: 3.10
Classifier: Programming Language :: Python :: 3.8
Classifier: Programming Language :: Python :: 3.9
Requires-Dist: more-itertools (>=8.12.0,<9.0.0)
Requires-Dist: numpy (>=1.22.2,<2.0.0)
Requires-Dist: pandas (>=1.4.1,<2.0.0)
Requires-Dist: pymongo (>=4.0.1,<5.0.0)
Requires-Dist: requests (>=2.27.1,<3.0.0)
Requires-Dist: scipy (>=1.8.0,<2.0.0)
Requires-Dist: types-requests (>=2.27.11,<3.0.0)
